pyifu/__init__.py
pyifu/adr.py
pyifu/adrfit.py
pyifu/mplinteractive.py
pyifu/spectroscopy.py
pyifu/tools.py
pyifu-0.13.0.data/scripts/display_cube.py
pyifu-0.13.0.dist-info/LICENSE
pyifu-0.13.0.dist-info/METADATA
pyifu-0.13.0.dist-info/WHEEL
pyifu-0.13.0.dist-info/top_level.txt
pyifu-0.13.0.dist-info/RECORD
